{
    "name": "SD1307",
    "version": "0.1.1",
    "dependencies": {
        "core": "*"
    },
    "files": [
        ".vscode/settings.json",
        ".vscode/tasks.json",
        "README.md",
        "_locales/zh-cn/SD1307-strings.json",
        "sd1307.ts",
        "test.ts",
        "tsconfig.json"
    ],
    "supportedTargets": [
        "microbit"
    ],
    "preferredEditor": "tsprj",
    "yotta": {
        "config": {
            "microbit-dal": {
                "bluetooth": {
                    "open": 0,
                    "whitelist": 1,
                    "security_level": "SECURITY_MODE_ENCRYPTION_NO_MITM"
                }
            }
        }
    }
}
